{"is_source_file": false, "format": "XML", "description": "This file is an Android vector drawable resource defining an app launcher icon with a background and a play button shape for TV.", "external_files": [], "external_methods": [], "published": [], "classes": [], "methods": [], "calls": [], "search-terms": ["ic_launcher", "vector drawable", "Android resource", "app icon", "TV icon", "drawable", "vector", "icon shape", "foreground icon", "app branding"], "state": 2, "file_id": 9, "knowledge_revision": 29, "git_revision": "865fad679a5fb204e6fd57578adb544a0555f765", "hash": "5f1228f93cb5a0eed3428fa4fe9b0b0b", "format-version": 4, "code-base-name": "android_tv_frontend", "filename": "android_tv_frontend/app/src/main/res/drawable/ic_launcher.xml", "revision_history": [{"29": "865fad679a5fb204e6fd57578adb544a0555f765"}]}